hrbdataproject/__init__.py
hrbdataproject/data_quality_checks.py
hrbdataproject/datachecks.py
hrbdataproject-2.5.dist-info/METADATA
hrbdataproject-2.5.dist-info/WHEEL
hrbdataproject-2.5.dist-info/top_level.txt
hrbdataproject-2.5.dist-info/RECORD
