Metadata-Version: 2.1
Name: hrbdataproject
Version: 2.5
Summary: A library for data quality checks in Databricks notebooks
Home-page: https://github.com/harunraseed/hrbdataproject
Author: Harun Raseed Basheer
Author-email: harun.raseed093@gmail.com
License: MIT
Classifier: Programming Language :: Python :: 3
Classifier: Operating System :: OS Independent
